sikriml_ner_spacy/__init__.py
sikriml_ner_spacy/spacy_processor.py
sikriml_ner_spacy/spacy_tokenizer.py
tests/__init__.py
tests/test_spacy_processor.py
sikriml_ner_spacy-0.1.1.dist-info/METADATA
sikriml_ner_spacy-0.1.1.dist-info/WHEEL
sikriml_ner_spacy-0.1.1.dist-info/top_level.txt
sikriml_ner_spacy-0.1.1.dist-info/RECORD
